flickpaysdk/__init__.py
flickpaysdk/flick.py
flickpaysdk-2.0.0.dist-info/LICENCE.txt
flickpaysdk-2.0.0.dist-info/METADATA
flickpaysdk-2.0.0.dist-info/WHEEL
flickpaysdk-2.0.0.dist-info/top_level.txt
flickpaysdk-2.0.0.dist-info/RECORD
