Metadata-Version: 2.1
Name: flickpaysdk
Version: 2.0.0
Summary: Flick Python SDKs contains FlickPay inflow and outflow solutions
Home-page: https://merchant.getflick.co/
Author: Qraba inc
Author-email: kingsley@getflick.app
License: MIT
Keywords: flickpaysdk,card,bank,transfer,payout,inflow,outflow
License-File: LICENCE.txt
